{
  "metadata": {
    "version": "1.0.0",
    "projectPath": "/Users/balovb/Documents/strava-activity-image-generator",
    "projectHash": "769262be2f0a",
    "lastModified": "2026-01-09T12:41:58.888Z",
    "sessionId": "1767962250257-5fp9ep"
  },
  "todos": [
    {
      "content": "Review and finalize system architecture specification",
      "status": "pending",
      "index": 0,
      "timestamp": "2026-01-09T12:41:58.888Z"
    },
    {
      "content": "Set up project structure with TypeScript configuration",
      "status": "pending",
      "index": 1,
      "timestamp": "2026-01-09T12:41:58.888Z"
    },
    {
      "content": "Implement Configuration Service (Phase 1 - Foundation)",
      "status": "pending",
      "index": 2,
      "timestamp": "2026-01-09T12:41:58.888Z"
    },
    {
      "content": "Implement Data Validation Service (Phase 1 - Foundation)",
      "status": "pending",
      "index": 3,
      "timestamp": "2026-01-09T12:41:58.888Z"
    },
    {
      "content": "Implement Logging Service (Phase 1 - Foundation)",
      "status": "pending",
      "index": 4,
      "timestamp": "2026-01-09T12:41:58.888Z"
    },
    {
      "content": "Implement Guardrails Service (Phase 1 - Foundation)",
      "status": "pending",
      "index": 5,
      "timestamp": "2026-01-09T12:41:58.888Z"
    },
    {
      "content": "Implement Text Processing Service (Phase 2 - Prompt Generation)",
      "status": "pending",
      "index": 6,
      "timestamp": "2026-01-09T12:41:58.888Z"
    },
    {
      "content": "Implement Signal Extraction Service (Phase 2 - Prompt Generation)",
      "status": "pending",
      "index": 7,
      "timestamp": "2026-01-09T12:41:58.888Z"
    },
    {
      "content": "Implement Style Selection Service (Phase 2 - Prompt Generation)",
      "status": "pending",
      "index": 8,
      "timestamp": "2026-01-09T12:41:58.888Z"
    },
    {
      "content": "Implement Mood Mapping Service (Phase 2 - Prompt Generation)",
      "status": "pending",
      "index": 9,
      "timestamp": "2026-01-09T12:41:58.888Z"
    },
    {
      "content": "Implement Prompt Generation Service (Phase 2 - Core Feature)",
      "status": "pending",
      "index": 10,
      "timestamp": "2026-01-09T12:41:58.888Z"
    },
    {
      "content": "Write unit tests for all Phase 1 services",
      "status": "pending",
      "index": 11,
      "timestamp": "2026-01-09T12:41:58.888Z"
    },
    {
      "content": "Write unit tests for all Phase 2 services",
      "status": "pending",
      "index": 12,
      "timestamp": "2026-01-09T12:41:58.888Z"
    },
    {
      "content": "Create integration tests for prompt generation flow",
      "status": "pending",
      "index": 13,
      "timestamp": "2026-01-09T12:41:58.888Z"
    },
    {
      "content": "Set up CI/CD pipeline",
      "status": "pending",
      "index": 14,
      "timestamp": "2026-01-09T12:41:58.888Z"
    },
    {
      "content": "Create example usage documentation",
      "status": "pending",
      "index": 15,
      "timestamp": "2026-01-09T12:41:58.888Z"
    }
  ]
}